rpa_amazon/__init__.py
rpa_amazon/api/__init__.py
rpa_amazon/command/__init__.py
rpa_amazon/command/bill/__init__.py
rpa_amazon/command/bill/service/__init__.py
rpa_amazon/request/__init__.py
rpa_amazon/service/__init__.py
rpa_amazon-1.0.0.dist-info/LICENSE
rpa_amazon-1.0.0.dist-info/METADATA
rpa_amazon-1.0.0.dist-info/WHEEL
rpa_amazon-1.0.0.dist-info/top_level.txt
rpa_amazon-1.0.0.dist-info/RECORD
